[
  {
    "id": 12,
    "title": "あなただけに ～It's only my Love～",
    "title_kana": "アナタダケニイッツオンリーマイラブ",
    "artist": "田村ゆかり"
  },
  {
    "id": 13,
    "title": "Baby's Breath",
    "title_kana": "ベイビーズブレス",
    "artist": "田村ゆかり"
  },
  {
    "id": 14,
    "title": "つぼみのままで",
    "title_kana": "ツボミノママデ",
    "artist": "田村ゆかり"
  },
  {
    "id": 15,
    "title": "interlude Ⅰ ～day's eye～",
    "title_kana": "インターリュード１デイズアイ",
    "artist": "田村ゆかり"
  },
  {
    "id": 16,
    "title": "さよならを　おしえて",
    "title_kana": "サヨナラヲオシエテ",
    "artist": "田村ゆかり"
  },
  {
    "id": 17,
    "title": "上海夜曲",
    "title_kana": "シャンハイヤキョク",
    "artist": "田村ゆかり"
  },
  {
    "id": 18,
    "title": "les larmes de la luna",
    "title_kana": "レラムデラルナ",
    "artist": "田村ゆかり"
  },
  {
    "id": 19,
    "title": "うたかた",
    "title_kana": "ウタカタ",
    "artist": "田村ゆかり"
  },
  {
    "id": 20,
    "title": "interlude Ⅱ ～milky way～",
    "title_kana": "インターリュード２ミルキーウェイ",
    "artist": "田村ゆかり"
  },
  {
    "id": 21,
    "title": "Love ♡ prade",
    "title_kana": "ラブパレード",
    "artist": "田村ゆかり"
  },
  {
    "id": 22,
    "title": "Fortune of Love",
    "title_kana": "フォーチュンオブラブ",
    "artist": "田村ゆかり"
  },
  {
    "id": 23,
    "title": "Eternity",
    "title_kana": "エタニティ",
    "artist": "田村ゆかり"
  },
  {
    "id": 24,
    "title": "Primary Tale",
    "title_kana": "プライマリーテイル",
    "artist": "田村ゆかり"
  },
  {
    "id": 25,
    "title": "Lovely Magic",
    "title_kana": "ラブリーマジック",
    "artist": "田村ゆかり"
  },
  {
    "id": 26,
    "title": "大好きと涙",
    "title_kana": "ダイスキトナミダ",
    "artist": "田村ゆかり"
  },
  {
    "id": 27,
    "title": "フルーツ",
    "title_kana": "フルーツ",
    "artist": "田村ゆかり"
  },
  {
    "id": 28,
    "title": "きらら時間旅行",
    "title_kana": "キララジカンリョコウ",
    "artist": "田村ゆかり"
  },
  {
    "id": 29,
    "title": "Snow bird",
    "title_kana": "スノーバード",
    "artist": "田村ゆかり"
  },
  {
    "id": 30,
    "title": "月華",
    "title_kana": "ゲッカ",
    "artist": "田村ゆかり"
  },
  {
    "id": 31,
    "title": "眠れぬ夜につかまえて",
    "title_kana": "ネムレヌヨルニツカマエテ",
    "artist": "田村ゆかり"
  },
  {
    "id": 32,
    "title": "虹の奇跡",
    "title_kana": "ニジノキセキ",
    "artist": "田村ゆかり"
  },
  {
    "id": 33,
    "title": "恋歌姫 ～蜜月夜バージョン～",
    "title_kana": "コイウタヒメミツゲツヤバージョン",
    "artist": "田村ゆかり"
  },
  {
    "id": 34,
    "title": "不可触な愛",
    "title_kana": "フカシンナアイ",
    "artist": "田村ゆかり"
  },
  {
    "id": 35,
    "title": "Honey Moon",
    "title_kana": "ハニームーン",
    "artist": "田村ゆかり"
  }
]
